mdformat_web/__init__.py
mdformat_web-0.2.0.dist-info/LICENSE
mdformat_web-0.2.0.dist-info/METADATA
mdformat_web-0.2.0.dist-info/WHEEL
mdformat_web-0.2.0.dist-info/entry_points.txt
mdformat_web-0.2.0.dist-info/RECORD
