Metadata-Version: 2.1
Name: mdformat-web
Version: 0.2.0
Summary: Mdformat plugin to format JS, CSS, HTML and XML code blocks
Home-page: https://github.com/hukkin/mdformat-web
License: MIT
Keywords: mdformat,markdown,commonmark,formatter
Author: Taneli Hukkinen
Author-email: hukkin@users.noreply.github.com
Requires-Python: >=3.9
Classifier: License :: OSI Approved :: MIT License
Classifier: Programming Language :: Python :: 3
Classifier: Programming Language :: Python :: 3.9
Classifier: Programming Language :: Python :: 3.10
Classifier: Programming Language :: Python :: 3.11
Classifier: Programming Language :: Python :: 3.12
Classifier: Programming Language :: Python :: 3.13
Classifier: Topic :: Documentation
Classifier: Topic :: Text Processing :: Markup
Classifier: Typing :: Typed
Requires-Dist: beautifulsoup4 (>=4.9.3)
Requires-Dist: cssbeautifier (>=1.13.0)
Requires-Dist: jsbeautifier (>=1.13.0)
Requires-Dist: mdformat (>=0.3.5)
Project-URL: Repository, https://github.com/hukkin/mdformat-web
